hss_server/__init__.py
hss_server/collection.py
hss_server/controller.py
hss_server/httptts.py
hss_server/logger.py
hss_server/mqtt.py
hss_server/rpc.py
hss_server/skill.py
hss_server/skillserver.py
hss_server-0.5.4.data/scripts/hss-cli
hss_server-0.5.4.data/scripts/hss-server
hss_server-0.5.4.dist-info/LICENSE
hss_server-0.5.4.dist-info/METADATA
hss_server-0.5.4.dist-info/WHEEL
hss_server-0.5.4.dist-info/top_level.txt
hss_server-0.5.4.dist-info/RECORD
