Metadata-Version: 2.1
Name: hss-server
Version: 0.5.4
Summary: Python-based skill server for the hermes MQTT protocol
Home-page: https://github.com/patrickjane/hss-server
Author: Patrick Fial
Author-email: mg.m@gmx.net
Classifier: Programming Language :: Python :: 3
Classifier: License :: OSI Approved :: MIT License
Classifier: Operating System :: OS Independent
Requires-Python: >=3.7
License-File: LICENSE
Requires-Dist: amqtt
Requires-Dist: requests
Requires-Dist: appdirs
Requires-Dist: GitPython
Requires-Dist: pid
